timedop
