Metadata-Version: 1.1
Name: timedop
Version: 0.0.7
Summary: Time python operations or enforce a time limit for function calls.
